[
{
"Queue": -1,
"Type": "dropped",
"Before": 38069,
"After": 38069
},
{
"Queue": 0,
"Type": "TX",
"Before": 15137341,
"After": 15248293
},
{
"Queue": 1,
"Type": "TX",
"Before": 10384871,
"After": 10384871
},
{
"Queue": 2,
"Type": "TX",
"Before": 9987227,
"After": 9987236
},
{
"Queue": 3,
"Type": "TX",
"Before": 5646809,
"After": 5847681
},
{
"Queue": 4,
"Type": "TX",
"Before": 5659012,
"After": 5977668
},
{
"Queue": 5,
"Type": "TX",
"Before": 4813804,
"After": 4926470
},
{
"Queue": 6,
"Type": "TX",
"Before": 7688220,
"After": 7836841
},
{
"Queue": 7,
"Type": "TX",
"Before": 4008305,
"After": 4149288
},
{
"Queue": 0,
"Type": "RX",
"Before": 1082218600,
"After": 1097825786
},
{
"Queue": 1,
"Type": "RX",
"Before": 325976823,
"After": 325976823
},
{
"Queue": 2,
"Type": "RX",
"Before": 255865898,
"After": 255865898
},
{
"Queue": 3,
"Type": "RX",
"Before": 341129596,
"After": 345591516
},
{
"Queue": 4,
"Type": "RX",
"Before": 259525593,
"After": 263983347
},
{
"Queue": 5,
"Type": "RX",
"Before": 202861763,
"After": 202861763
},
{
"Queue": 6,
"Type": "RX",
"Before": 251330154,
"After": 266921806
},
{
"Queue": 7,
"Type": "RX",
"Before": 182924039,
"After": 187387433
}
]