[
{
"CPU": 0,
"Processed": 0,
"Dropped": 0,
"Squeezed": 0,
"RPS Interrupts": 0,
"IPI Enqueued": 0,
"InputQ Dequeued": 0,
"Input Pkts": 0
},
{
"CPU": 1,
"Processed": 259682,
"Dropped": 0,
"Squeezed": 0,
"RPS Interrupts": 157072,
"IPI Enqueued": 157072,
"InputQ Dequeued": 177604,
"Input Pkts": 259682
},
{
"CPU": 2,
"Processed": 563677,
"Dropped": 0,
"Squeezed": 0,
"RPS Interrupts": 358259,
"IPI Enqueued": 358259,
"InputQ Dequeued": 394288,
"Input Pkts": 563677
},
{
"CPU": 3,
"Processed": 87270,
"Dropped": 0,
"Squeezed": 0,
"RPS Interrupts": 53297,
"IPI Enqueued": 53297,
"InputQ Dequeued": 59396,
"Input Pkts": 87270
},
{
"CPU": 4,
"Processed": 386096,
"Dropped": 0,
"Squeezed": 0,
"RPS Interrupts": 242343,
"IPI Enqueued": 242343,
"InputQ Dequeued": 266831,
"Input Pkts": 386096
},
{
"CPU": 5,
"Processed": 238,
"Dropped": 0,
"Squeezed": 0,
"RPS Interrupts": 18,
"IPI Enqueued": 18,
"InputQ Dequeued": 49,
"Input Pkts": 238
},
{
"CPU": 6,
"Processed": 0,
"Dropped": 0,
"Squeezed": 0,
"RPS Interrupts": 0,
"IPI Enqueued": 0,
"InputQ Dequeued": 0,
"Input Pkts": 0
},
{
"CPU": 7,
"Processed": 0,
"Dropped": 0,
"Squeezed": 0,
"RPS Interrupts": 0,
"IPI Enqueued": 0,
"InputQ Dequeued": 0,
"Input Pkts": 0
},
{
"CPU": 8,
"Processed": 0,
"Dropped": 0,
"Squeezed": 0,
"RPS Interrupts": 0,
"IPI Enqueued": 0,
"InputQ Dequeued": 0,
"Input Pkts": 0
},
{
"CPU": 9,
"Processed": 0,
"Dropped": 0,
"Squeezed": 0,
"RPS Interrupts": 0,
"IPI Enqueued": 0,
"InputQ Dequeued": 0,
"Input Pkts": 0
},
{
"CPU": 10,
"Processed": 0,
"Dropped": 0,
"Squeezed": 0,
"RPS Interrupts": 0,
"IPI Enqueued": 0,
"InputQ Dequeued": 0,
"Input Pkts": 0
},
{
"CPU": 11,
"Processed": 0,
"Dropped": 0,
"Squeezed": 0,
"RPS Interrupts": 0,
"IPI Enqueued": 0,
"InputQ Dequeued": 0,
"Input Pkts": 0
},
{
"CPU": 12,
"Processed": 0,
"Dropped": 0,
"Squeezed": 0,
"RPS Interrupts": 0,
"IPI Enqueued": 0,
"InputQ Dequeued": 0,
"Input Pkts": 0
},
{
"CPU": 13,
"Processed": 0,
"Dropped": 0,
"Squeezed": 0,
"RPS Interrupts": 0,
"IPI Enqueued": 0,
"InputQ Dequeued": 0,
"Input Pkts": 0
},
{
"CPU": 14,
"Processed": 0,
"Dropped": 0,
"Squeezed": 0,
"RPS Interrupts": 0,
"IPI Enqueued": 0,
"InputQ Dequeued": 0,
"Input Pkts": 0
},
{
"CPU": 15,
"Processed": 0,
"Dropped": 0,
"Squeezed": 0,
"RPS Interrupts": 0,
"IPI Enqueued": 0,
"InputQ Dequeued": 0,
"Input Pkts": 0
},
{
"CPU": 16,
"Processed": 0,
"Dropped": 0,
"Squeezed": 0,
"RPS Interrupts": 0,
"IPI Enqueued": 0,
"InputQ Dequeued": 0,
"Input Pkts": 0
},
{
"CPU": 17,
"Processed": 0,
"Dropped": 0,
"Squeezed": 0,
"RPS Interrupts": 0,
"IPI Enqueued": 0,
"InputQ Dequeued": 0,
"Input Pkts": 0
},
{
"CPU": 18,
"Processed": 0,
"Dropped": 0,
"Squeezed": 0,
"RPS Interrupts": 0,
"IPI Enqueued": 0,
"InputQ Dequeued": 0,
"Input Pkts": 0
},
{
"CPU": 19,
"Processed": 0,
"Dropped": 0,
"Squeezed": 0,
"RPS Interrupts": 0,
"IPI Enqueued": 0,
"InputQ Dequeued": 0,
"Input Pkts": 0
},
{
"CPU": 20,
"Processed": 0,
"Dropped": 0,
"Squeezed": 0,
"RPS Interrupts": 0,
"IPI Enqueued": 0,
"InputQ Dequeued": 0,
"Input Pkts": 0
},
{
"CPU": 21,
"Processed": 0,
"Dropped": 0,
"Squeezed": 0,
"RPS Interrupts": 0,
"IPI Enqueued": 0,
"InputQ Dequeued": 0,
"Input Pkts": 0
},
{
"CPU": 22,
"Processed": 0,
"Dropped": 0,
"Squeezed": 0,
"RPS Interrupts": 0,
"IPI Enqueued": 0,
"InputQ Dequeued": 0,
"Input Pkts": 0
},
{
"CPU": 23,
"Processed": 0,
"Dropped": 0,
"Squeezed": 0,
"RPS Interrupts": 0,
"IPI Enqueued": 0,
"InputQ Dequeued": 0,
"Input Pkts": 0
},
{
"CPU": 24,
"Processed": 0,
"Dropped": 0,
"Squeezed": 0,
"RPS Interrupts": 0,
"IPI Enqueued": 0,
"InputQ Dequeued": 0,
"Input Pkts": 0
},
{
"CPU": 25,
"Processed": 0,
"Dropped": 0,
"Squeezed": 0,
"RPS Interrupts": 0,
"IPI Enqueued": 0,
"InputQ Dequeued": 0,
"Input Pkts": 0
},
{
"CPU": 26,
"Processed": 0,
"Dropped": 0,
"Squeezed": 0,
"RPS Interrupts": 0,
"IPI Enqueued": 0,
"InputQ Dequeued": 0,
"Input Pkts": 0
},
{
"CPU": 27,
"Processed": 0,
"Dropped": 0,
"Squeezed": 0,
"RPS Interrupts": 0,
"IPI Enqueued": 0,
"InputQ Dequeued": 0,
"Input Pkts": 0
},
{
"CPU": 28,
"Processed": 0,
"Dropped": 0,
"Squeezed": 0,
"RPS Interrupts": 0,
"IPI Enqueued": 0,
"InputQ Dequeued": 0,
"Input Pkts": 0
},
{
"CPU": 29,
"Processed": 0,
"Dropped": 0,
"Squeezed": 0,
"RPS Interrupts": 0,
"IPI Enqueued": 0,
"InputQ Dequeued": 0,
"Input Pkts": 0
},
{
"CPU": 30,
"Processed": 0,
"Dropped": 0,
"Squeezed": 0,
"RPS Interrupts": 0,
"IPI Enqueued": 0,
"InputQ Dequeued": 0,
"Input Pkts": 0
},
{
"CPU": 31,
"Processed": 0,
"Dropped": 0,
"Squeezed": 0,
"RPS Interrupts": 0,
"IPI Enqueued": 0,
"InputQ Dequeued": 0,
"Input Pkts": 0
},
{
"CPU": 32,
"Processed": 0,
"Dropped": 0,
"Squeezed": 0,
"RPS Interrupts": 0,
"IPI Enqueued": 0,
"InputQ Dequeued": 0,
"Input Pkts": 0
},
{
"CPU": 33,
"Processed": 0,
"Dropped": 0,
"Squeezed": 0,
"RPS Interrupts": 0,
"IPI Enqueued": 0,
"InputQ Dequeued": 0,
"Input Pkts": 0
},
{
"CPU": 34,
"Processed": 0,
"Dropped": 0,
"Squeezed": 0,
"RPS Interrupts": 0,
"IPI Enqueued": 0,
"InputQ Dequeued": 0,
"Input Pkts": 0
},
{
"CPU": 35,
"Processed": 0,
"Dropped": 0,
"Squeezed": 0,
"RPS Interrupts": 0,
"IPI Enqueued": 0,
"InputQ Dequeued": 0,
"Input Pkts": 0
}
]