[
{
"start": 0,
"end": 50,
"count": 3728634
},
{
"start": 50,
"end": 100,
"count": 816455
},
{
"start": 100,
"end": 150,
"count": 156497
},
{
"start": 150,
"end": 200,
"count": 36455
},
{
"start": 200,
"end": 250,
"count": 21088
},
{
"start": 250,
"end": 300,
"count": 23620
},
{
"start": 300,
"end": 350,
"count": 3070
},
{
"start": 350,
"end": 400,
"count": 900
},
{
"start": 400,
"end": 450,
"count": 509
},
{
"start": 450,
"end": 500,
"count": 355
},
{
"start": 500,
"end": 550,
"count": 206
},
{
"start": 550,
"end": 600,
"count": 113
},
{
"start": 600,
"end": 650,
"count": 124
},
{
"start": 650,
"end": 700,
"count": 76
},
{
"start": 700,
"end": 750,
"count": 78
},
{
"start": 750,
"end": 800,
"count": 59
},
{
"start": 800,
"end": 850,
"count": 51
},
{
"start": 850,
"end": 900,
"count": 36
},
{
"start": 900,
"end": 950,
"count": 29
},
{
"start": 950,
"end": 1000,
"count": 473
}
]