[
{
"Queue": -1,
"Type": "dropped",
"Before": 37332069,
"After": 37332069
},
{
"Queue": 0,
"Type": "TX",
"Before": 289527109,
"After": 289794226
},
{
"Queue": 1,
"Type": "TX",
"Before": 13627907,
"After": 13830122
},
{
"Queue": 2,
"Type": "TX",
"Before": 13565823,
"After": 14216649
},
{
"Queue": 3,
"Type": "TX",
"Before": 12118924,
"After": 12590502
},
{
"Queue": 0,
"Type": "RX",
"Before": 11095916833,
"After": 11108911408
},
{
"Queue": 1,
"Type": "RX",
"Before": 593522090,
"After": 606518250
},
{
"Queue": 2,
"Type": "RX",
"Before": 484190827,
"After": 489760390
},
{
"Queue": 3,
"Type": "RX",
"Before": 492753421,
"After": 505748628
}
]