[
{
"CPU": 0,
"Total": 175214,
"PrevInvalid": 0,
"PrevIdle": 158660,
"AssignedToBusy": 67304,
"NoBusyAvailable": 91356,
"TargetIsSelf": 23460,
"ChoseInvalid": 0,
"Fallback": 0
},
{
"CPU": 1,
"Total": 270925,
"PrevInvalid": 3,
"PrevIdle": 256541,
"AssignedToBusy": 105496,
"NoBusyAvailable": 151048,
"TargetIsSelf": 18316,
"ChoseInvalid": 0,
"Fallback": 6
},
{
"CPU": 2,
"Total": 233353,
"PrevInvalid": 1,
"PrevIdle": 228851,
"AssignedToBusy": 109880,
"NoBusyAvailable": 118972,
"TargetIsSelf": 5813,
"ChoseInvalid": 0,
"Fallback": 2
},
{
"CPU": 3,
"Total": 488882,
"PrevInvalid": 0,
"PrevIdle": 478290,
"AssignedToBusy": 214266,
"NoBusyAvailable": 264024,
"TargetIsSelf": 13816,
"ChoseInvalid": 0,
"Fallback": 0
},
{
"CPU": 4,
"Total": 393663,
"PrevInvalid": 1,
"PrevIdle": 321672,
"AssignedToBusy": 142919,
"NoBusyAvailable": 178754,
"TargetIsSelf": 92558,
"ChoseInvalid": 0,
"Fallback": 2
},
{
"CPU": 5,
"Total": 103593,
"PrevInvalid": 2,
"PrevIdle": 95195,
"AssignedToBusy": 41279,
"NoBusyAvailable": 53918,
"TargetIsSelf": 9893,
"ChoseInvalid": 0,
"Fallback": 3
},
{
"CPU": 6,
"Total": 445437,
"PrevInvalid": 0,
"PrevIdle": 350648,
"AssignedToBusy": 154486,
"NoBusyAvailable": 196162,
"TargetIsSelf": 120040,
"ChoseInvalid": 0,
"Fallback": 0
},
{
"CPU": 7,
"Total": 83691,
"PrevInvalid": 0,
"PrevIdle": 74386,
"AssignedToBusy": 32126,
"NoBusyAvailable": 42260,
"TargetIsSelf": 10611,
"ChoseInvalid": 0,
"Fallback": 0
},
{
"CPU": 8,
"Total": 0,
"PrevInvalid": 0,
"PrevIdle": 0,
"AssignedToBusy": 0,
"NoBusyAvailable": 0,
"TargetIsSelf": 0,
"ChoseInvalid": 0,
"Fallback": 0
},
{
"CPU": 9,
"Total": 0,
"PrevInvalid": 0,
"PrevIdle": 0,
"AssignedToBusy": 0,
"NoBusyAvailable": 0,
"TargetIsSelf": 0,
"ChoseInvalid": 0,
"Fallback": 0
},
{
"CPU": 10,
"Total": 0,
"PrevInvalid": 0,
"PrevIdle": 0,
"AssignedToBusy": 0,
"NoBusyAvailable": 0,
"TargetIsSelf": 0,
"ChoseInvalid": 0,
"Fallback": 0
},
{
"CPU": 11,
"Total": 0,
"PrevInvalid": 0,
"PrevIdle": 0,
"AssignedToBusy": 0,
"NoBusyAvailable": 0,
"TargetIsSelf": 0,
"ChoseInvalid": 0,
"Fallback": 0
},
{
"CPU": 12,
"Total": 0,
"PrevInvalid": 0,
"PrevIdle": 0,
"AssignedToBusy": 0,
"NoBusyAvailable": 0,
"TargetIsSelf": 0,
"ChoseInvalid": 0,
"Fallback": 0
},
{
"CPU": 13,
"Total": 632,
"PrevInvalid": 0,
"PrevIdle": 0,
"AssignedToBusy": 0,
"NoBusyAvailable": 0,
"TargetIsSelf": 0,
"ChoseInvalid": 0,
"Fallback": 0
},
{
"CPU": 14,
"Total": 0,
"PrevInvalid": 0,
"PrevIdle": 0,
"AssignedToBusy": 0,
"NoBusyAvailable": 0,
"TargetIsSelf": 0,
"ChoseInvalid": 0,
"Fallback": 0
},
{
"CPU": 15,
"Total": 0,
"PrevInvalid": 0,
"PrevIdle": 0,
"AssignedToBusy": 0,
"NoBusyAvailable": 0,
"TargetIsSelf": 0,
"ChoseInvalid": 0,
"Fallback": 0
},
{
"CPU": 16,
"Total": 0,
"PrevInvalid": 0,
"PrevIdle": 0,
"AssignedToBusy": 0,
"NoBusyAvailable": 0,
"TargetIsSelf": 0,
"ChoseInvalid": 0,
"Fallback": 0
},
{
"CPU": 17,
"Total": 0,
"PrevInvalid": 0,
"PrevIdle": 0,
"AssignedToBusy": 0,
"NoBusyAvailable": 0,
"TargetIsSelf": 0,
"ChoseInvalid": 0,
"Fallback": 0
},
{
"CPU": 18,
"Total": 0,
"PrevInvalid": 0,
"PrevIdle": 0,
"AssignedToBusy": 0,
"NoBusyAvailable": 0,
"TargetIsSelf": 0,
"ChoseInvalid": 0,
"Fallback": 0
},
{
"CPU": 19,
"Total": 0,
"PrevInvalid": 0,
"PrevIdle": 0,
"AssignedToBusy": 0,
"NoBusyAvailable": 0,
"TargetIsSelf": 0,
"ChoseInvalid": 0,
"Fallback": 0
},
{
"CPU": 20,
"Total": 0,
"PrevInvalid": 0,
"PrevIdle": 0,
"AssignedToBusy": 0,
"NoBusyAvailable": 0,
"TargetIsSelf": 0,
"ChoseInvalid": 0,
"Fallback": 0
},
{
"CPU": 21,
"Total": 0,
"PrevInvalid": 0,
"PrevIdle": 0,
"AssignedToBusy": 0,
"NoBusyAvailable": 0,
"TargetIsSelf": 0,
"ChoseInvalid": 0,
"Fallback": 0
},
{
"CPU": 22,
"Total": 0,
"PrevInvalid": 0,
"PrevIdle": 0,
"AssignedToBusy": 0,
"NoBusyAvailable": 0,
"TargetIsSelf": 0,
"ChoseInvalid": 0,
"Fallback": 0
},
{
"CPU": 23,
"Total": 0,
"PrevInvalid": 0,
"PrevIdle": 0,
"AssignedToBusy": 0,
"NoBusyAvailable": 0,
"TargetIsSelf": 0,
"ChoseInvalid": 0,
"Fallback": 0
},
{
"CPU": 24,
"Total": 0,
"PrevInvalid": 0,
"PrevIdle": 0,
"AssignedToBusy": 0,
"NoBusyAvailable": 0,
"TargetIsSelf": 0,
"ChoseInvalid": 0,
"Fallback": 0
},
{
"CPU": 25,
"Total": 0,
"PrevInvalid": 0,
"PrevIdle": 0,
"AssignedToBusy": 0,
"NoBusyAvailable": 0,
"TargetIsSelf": 0,
"ChoseInvalid": 0,
"Fallback": 0
},
{
"CPU": 26,
"Total": 0,
"PrevInvalid": 0,
"PrevIdle": 0,
"AssignedToBusy": 0,
"NoBusyAvailable": 0,
"TargetIsSelf": 0,
"ChoseInvalid": 0,
"Fallback": 0
},
{
"CPU": 27,
"Total": 0,
"PrevInvalid": 0,
"PrevIdle": 0,
"AssignedToBusy": 0,
"NoBusyAvailable": 0,
"TargetIsSelf": 0,
"ChoseInvalid": 0,
"Fallback": 0
},
{
"CPU": 28,
"Total": 0,
"PrevInvalid": 0,
"PrevIdle": 0,
"AssignedToBusy": 0,
"NoBusyAvailable": 0,
"TargetIsSelf": 0,
"ChoseInvalid": 0,
"Fallback": 0
},
{
"CPU": 29,
"Total": 0,
"PrevInvalid": 0,
"PrevIdle": 0,
"AssignedToBusy": 0,
"NoBusyAvailable": 0,
"TargetIsSelf": 0,
"ChoseInvalid": 0,
"Fallback": 0
},
{
"CPU": 30,
"Total": 0,
"PrevInvalid": 0,
"PrevIdle": 0,
"AssignedToBusy": 0,
"NoBusyAvailable": 0,
"TargetIsSelf": 0,
"ChoseInvalid": 0,
"Fallback": 0
},
{
"CPU": 31,
"Total": 0,
"PrevInvalid": 0,
"PrevIdle": 0,
"AssignedToBusy": 0,
"NoBusyAvailable": 0,
"TargetIsSelf": 0,
"ChoseInvalid": 0,
"Fallback": 0
},
{
"CPU": 32,
"Total": 0,
"PrevInvalid": 0,
"PrevIdle": 0,
"AssignedToBusy": 0,
"NoBusyAvailable": 0,
"TargetIsSelf": 0,
"ChoseInvalid": 0,
"Fallback": 0
},
{
"CPU": 33,
"Total": 0,
"PrevInvalid": 0,
"PrevIdle": 0,
"AssignedToBusy": 0,
"NoBusyAvailable": 0,
"TargetIsSelf": 0,
"ChoseInvalid": 0,
"Fallback": 0
},
{
"CPU": 34,
"Total": 0,
"PrevInvalid": 0,
"PrevIdle": 0,
"AssignedToBusy": 0,
"NoBusyAvailable": 0,
"TargetIsSelf": 0,
"ChoseInvalid": 0,
"Fallback": 0
},
{
"CPU": 35,
"Total": 0,
"PrevInvalid": 0,
"PrevIdle": 0,
"AssignedToBusy": 0,
"NoBusyAvailable": 0,
"TargetIsSelf": 0,
"ChoseInvalid": 0,
"Fallback": 0
}
]