[
{
"Queue": -1,
"Type": "dropped",
"Before": 60528,
"After": 60528
},
{
"Queue": 0,
"Type": "TX",
"Before": 109888673,
"After": 111014770
},
{
"Queue": 1,
"Type": "TX",
"Before": 93817712,
"After": 94657854
},
{
"Queue": 2,
"Type": "TX",
"Before": 93810100,
"After": 94637510
},
{
"Queue": 3,
"Type": "TX",
"Before": 117581641,
"After": 118629342
},
{
"Queue": 0,
"Type": "RX",
"Before": 1891405774,
"After": 1907452169
},
{
"Queue": 1,
"Type": "RX",
"Before": 1870091437,
"After": 1878747315
},
{
"Queue": 2,
"Type": "RX",
"Before": 2083675498,
"After": 2098493033
},
{
"Queue": 3,
"Type": "RX",
"Before": 1793114813,
"After": 1798067523
}
]