[
{
"Queue": -1,
"Type": "dropped",
"Before": 69979761,
"After": 70006799
},
{
"Queue": 0,
"Type": "TX",
"Before": 559968152,
"After": 559968165
},
{
"Queue": 1,
"Type": "TX",
"Before": 343929,
"After": 343929
},
{
"Queue": 2,
"Type": "TX",
"Before": 43,
"After": 43
},
{
"Queue": 3,
"Type": "TX",
"Before": 353968,
"After": 353968
},
{
"Queue": 4,
"Type": "TX",
"Before": 343780,
"After": 343780
},
{
"Queue": 5,
"Type": "TX",
"Before": 319190,
"After": 319211
},
{
"Queue": 6,
"Type": "TX",
"Before": 325020,
"After": 325033
},
{
"Queue": 7,
"Type": "TX",
"Before": 59,
"After": 768274
},
{
"Queue": 0,
"Type": "RX",
"Before": 20688105426,
"After": 20688105426
},
{
"Queue": 1,
"Type": "RX",
"Before": 57334186,
"After": 57334186
},
{
"Queue": 2,
"Type": "RX",
"Before": 57655876,
"After": 57655876
},
{
"Queue": 3,
"Type": "RX",
"Before": 56487119,
"After": 56487133
},
{
"Queue": 4,
"Type": "RX",
"Before": 56200810,
"After": 56200810
},
{
"Queue": 5,
"Type": "RX",
"Before": 30,
"After": 30
},
{
"Queue": 6,
"Type": "RX",
"Before": 0,
"After": 0
},
{
"Queue": 7,
"Type": "RX",
"Before": 115100741,
"After": 166239059
}
]