[
{
"CPU": 0,
"Processed": 24,
"Dropped": 0,
"Squeezed": 0,
"RPS Interrupts": 0
},
{
"CPU": 1,
"Processed": 473924,
"Dropped": 0,
"Squeezed": 0,
"RPS Interrupts": 23557
},
{
"CPU": 2,
"Processed": 505514,
"Dropped": 0,
"Squeezed": 0,
"RPS Interrupts": 25039
},
{
"CPU": 3,
"Processed": 429424,
"Dropped": 0,
"Squeezed": 0,
"RPS Interrupts": 20918
},
{
"CPU": 4,
"Processed": 567556,
"Dropped": 0,
"Squeezed": 0,
"RPS Interrupts": 27721
},
{
"CPU": 5,
"Processed": 349354,
"Dropped": 0,
"Squeezed": 0,
"RPS Interrupts": 17108
},
{
"CPU": 6,
"Processed": 541309,
"Dropped": 0,
"Squeezed": 0,
"RPS Interrupts": 26539
},
{
"CPU": 7,
"Processed": 103933,
"Dropped": 0,
"Squeezed": 0,
"RPS Interrupts": 5152
},
{
"CPU": 8,
"Processed": 0,
"Dropped": 0,
"Squeezed": 0,
"RPS Interrupts": 0
},
{
"CPU": 9,
"Processed": 0,
"Dropped": 0,
"Squeezed": 0,
"RPS Interrupts": 0
},
{
"CPU": 10,
"Processed": 0,
"Dropped": 0,
"Squeezed": 0,
"RPS Interrupts": 0
},
{
"CPU": 11,
"Processed": 0,
"Dropped": 0,
"Squeezed": 0,
"RPS Interrupts": 0
},
{
"CPU": 12,
"Processed": 0,
"Dropped": 0,
"Squeezed": 0,
"RPS Interrupts": 0
},
{
"CPU": 13,
"Processed": 680,
"Dropped": 0,
"Squeezed": 0,
"RPS Interrupts": 0
},
{
"CPU": 14,
"Processed": 0,
"Dropped": 0,
"Squeezed": 0,
"RPS Interrupts": 0
},
{
"CPU": 15,
"Processed": 0,
"Dropped": 0,
"Squeezed": 0,
"RPS Interrupts": 0
},
{
"CPU": 16,
"Processed": 0,
"Dropped": 0,
"Squeezed": 0,
"RPS Interrupts": 0
},
{
"CPU": 17,
"Processed": 0,
"Dropped": 0,
"Squeezed": 0,
"RPS Interrupts": 0
},
{
"CPU": 18,
"Processed": 0,
"Dropped": 0,
"Squeezed": 0,
"RPS Interrupts": 0
},
{
"CPU": 19,
"Processed": 0,
"Dropped": 0,
"Squeezed": 0,
"RPS Interrupts": 0
},
{
"CPU": 20,
"Processed": 0,
"Dropped": 0,
"Squeezed": 0,
"RPS Interrupts": 0
},
{
"CPU": 21,
"Processed": 0,
"Dropped": 0,
"Squeezed": 0,
"RPS Interrupts": 0
},
{
"CPU": 22,
"Processed": 0,
"Dropped": 0,
"Squeezed": 0,
"RPS Interrupts": 0
},
{
"CPU": 23,
"Processed": 0,
"Dropped": 0,
"Squeezed": 0,
"RPS Interrupts": 0
},
{
"CPU": 24,
"Processed": 0,
"Dropped": 0,
"Squeezed": 0,
"RPS Interrupts": 0
},
{
"CPU": 25,
"Processed": 0,
"Dropped": 0,
"Squeezed": 0,
"RPS Interrupts": 0
},
{
"CPU": 26,
"Processed": 0,
"Dropped": 0,
"Squeezed": 0,
"RPS Interrupts": 0
},
{
"CPU": 27,
"Processed": 0,
"Dropped": 0,
"Squeezed": 0,
"RPS Interrupts": 0
},
{
"CPU": 28,
"Processed": 0,
"Dropped": 0,
"Squeezed": 0,
"RPS Interrupts": 0
},
{
"CPU": 29,
"Processed": 0,
"Dropped": 0,
"Squeezed": 0,
"RPS Interrupts": 0
},
{
"CPU": 30,
"Processed": 0,
"Dropped": 0,
"Squeezed": 0,
"RPS Interrupts": 0
},
{
"CPU": 31,
"Processed": 0,
"Dropped": 0,
"Squeezed": 0,
"RPS Interrupts": 0
},
{
"CPU": 32,
"Processed": 0,
"Dropped": 0,
"Squeezed": 0,
"RPS Interrupts": 0
},
{
"CPU": 33,
"Processed": 0,
"Dropped": 0,
"Squeezed": 0,
"RPS Interrupts": 0
},
{
"CPU": 34,
"Processed": 0,
"Dropped": 0,
"Squeezed": 0,
"RPS Interrupts": 0
},
{
"CPU": 35,
"Processed": 0,
"Dropped": 0,
"Squeezed": 0,
"RPS Interrupts": 0
}
]