[
{
"CPU": 0,
"Processed": 18,
"Dropped": 0,
"Squeezed": 0,
"RPS Interrupts": 0,
"IPI Enqueued": 0,
"InputQ Dequeued": 0,
"Input Pkts": 0
},
{
"CPU": 1,
"Processed": 203215,
"Dropped": 0,
"Squeezed": 0,
"RPS Interrupts": 154379,
"IPI Enqueued": 154379,
"InputQ Dequeued": 184810,
"Input Pkts": 203215
},
{
"CPU": 2,
"Processed": 203838,
"Dropped": 0,
"Squeezed": 0,
"RPS Interrupts": 143939,
"IPI Enqueued": 143939,
"InputQ Dequeued": 186641,
"Input Pkts": 203838
},
{
"CPU": 3,
"Processed": 178813,
"Dropped": 0,
"Squeezed": 0,
"RPS Interrupts": 138635,
"IPI Enqueued": 138635,
"InputQ Dequeued": 164842,
"Input Pkts": 178813
},
{
"CPU": 4,
"Processed": 244489,
"Dropped": 0,
"Squeezed": 0,
"RPS Interrupts": 193201,
"IPI Enqueued": 193201,
"InputQ Dequeued": 225937,
"Input Pkts": 244489
},
{
"CPU": 5,
"Processed": 113771,
"Dropped": 0,
"Squeezed": 0,
"RPS Interrupts": 82544,
"IPI Enqueued": 82544,
"InputQ Dequeued": 104268,
"Input Pkts": 113771
},
{
"CPU": 6,
"Processed": 234639,
"Dropped": 0,
"Squeezed": 0,
"RPS Interrupts": 184693,
"IPI Enqueued": 184693,
"InputQ Dequeued": 216716,
"Input Pkts": 234639
},
{
"CPU": 7,
"Processed": 19322,
"Dropped": 0,
"Squeezed": 0,
"RPS Interrupts": 13140,
"IPI Enqueued": 13140,
"InputQ Dequeued": 17724,
"Input Pkts": 19322
},
{
"CPU": 8,
"Processed": 0,
"Dropped": 0,
"Squeezed": 0,
"RPS Interrupts": 0,
"IPI Enqueued": 0,
"InputQ Dequeued": 0,
"Input Pkts": 0
},
{
"CPU": 9,
"Processed": 0,
"Dropped": 0,
"Squeezed": 0,
"RPS Interrupts": 0,
"IPI Enqueued": 0,
"InputQ Dequeued": 0,
"Input Pkts": 0
},
{
"CPU": 10,
"Processed": 0,
"Dropped": 0,
"Squeezed": 0,
"RPS Interrupts": 0,
"IPI Enqueued": 0,
"InputQ Dequeued": 0,
"Input Pkts": 0
},
{
"CPU": 11,
"Processed": 0,
"Dropped": 0,
"Squeezed": 0,
"RPS Interrupts": 0,
"IPI Enqueued": 0,
"InputQ Dequeued": 0,
"Input Pkts": 0
},
{
"CPU": 12,
"Processed": 0,
"Dropped": 0,
"Squeezed": 0,
"RPS Interrupts": 0,
"IPI Enqueued": 0,
"InputQ Dequeued": 0,
"Input Pkts": 0
},
{
"CPU": 13,
"Processed": 677,
"Dropped": 0,
"Squeezed": 0,
"RPS Interrupts": 0,
"IPI Enqueued": 0,
"InputQ Dequeued": 0,
"Input Pkts": 0
},
{
"CPU": 14,
"Processed": 0,
"Dropped": 0,
"Squeezed": 0,
"RPS Interrupts": 0,
"IPI Enqueued": 0,
"InputQ Dequeued": 0,
"Input Pkts": 0
},
{
"CPU": 15,
"Processed": 0,
"Dropped": 0,
"Squeezed": 0,
"RPS Interrupts": 0,
"IPI Enqueued": 0,
"InputQ Dequeued": 0,
"Input Pkts": 0
},
{
"CPU": 16,
"Processed": 0,
"Dropped": 0,
"Squeezed": 0,
"RPS Interrupts": 0,
"IPI Enqueued": 0,
"InputQ Dequeued": 0,
"Input Pkts": 0
},
{
"CPU": 17,
"Processed": 0,
"Dropped": 0,
"Squeezed": 0,
"RPS Interrupts": 0,
"IPI Enqueued": 0,
"InputQ Dequeued": 0,
"Input Pkts": 0
},
{
"CPU": 18,
"Processed": 0,
"Dropped": 0,
"Squeezed": 0,
"RPS Interrupts": 0,
"IPI Enqueued": 0,
"InputQ Dequeued": 0,
"Input Pkts": 0
},
{
"CPU": 19,
"Processed": 0,
"Dropped": 0,
"Squeezed": 0,
"RPS Interrupts": 0,
"IPI Enqueued": 0,
"InputQ Dequeued": 0,
"Input Pkts": 0
},
{
"CPU": 20,
"Processed": 0,
"Dropped": 0,
"Squeezed": 0,
"RPS Interrupts": 0,
"IPI Enqueued": 0,
"InputQ Dequeued": 0,
"Input Pkts": 0
},
{
"CPU": 21,
"Processed": 0,
"Dropped": 0,
"Squeezed": 0,
"RPS Interrupts": 0,
"IPI Enqueued": 0,
"InputQ Dequeued": 0,
"Input Pkts": 0
},
{
"CPU": 22,
"Processed": 0,
"Dropped": 0,
"Squeezed": 0,
"RPS Interrupts": 0,
"IPI Enqueued": 0,
"InputQ Dequeued": 0,
"Input Pkts": 0
},
{
"CPU": 23,
"Processed": 0,
"Dropped": 0,
"Squeezed": 0,
"RPS Interrupts": 0,
"IPI Enqueued": 0,
"InputQ Dequeued": 0,
"Input Pkts": 0
},
{
"CPU": 24,
"Processed": 0,
"Dropped": 0,
"Squeezed": 0,
"RPS Interrupts": 0,
"IPI Enqueued": 0,
"InputQ Dequeued": 0,
"Input Pkts": 0
},
{
"CPU": 25,
"Processed": 0,
"Dropped": 0,
"Squeezed": 0,
"RPS Interrupts": 0,
"IPI Enqueued": 0,
"InputQ Dequeued": 0,
"Input Pkts": 0
},
{
"CPU": 26,
"Processed": 0,
"Dropped": 0,
"Squeezed": 0,
"RPS Interrupts": 0,
"IPI Enqueued": 0,
"InputQ Dequeued": 0,
"Input Pkts": 0
},
{
"CPU": 27,
"Processed": 0,
"Dropped": 0,
"Squeezed": 0,
"RPS Interrupts": 0,
"IPI Enqueued": 0,
"InputQ Dequeued": 0,
"Input Pkts": 0
},
{
"CPU": 28,
"Processed": 0,
"Dropped": 0,
"Squeezed": 0,
"RPS Interrupts": 0,
"IPI Enqueued": 0,
"InputQ Dequeued": 0,
"Input Pkts": 0
},
{
"CPU": 29,
"Processed": 0,
"Dropped": 0,
"Squeezed": 0,
"RPS Interrupts": 0,
"IPI Enqueued": 0,
"InputQ Dequeued": 0,
"Input Pkts": 0
},
{
"CPU": 30,
"Processed": 0,
"Dropped": 0,
"Squeezed": 0,
"RPS Interrupts": 0,
"IPI Enqueued": 0,
"InputQ Dequeued": 0,
"Input Pkts": 0
},
{
"CPU": 31,
"Processed": 0,
"Dropped": 0,
"Squeezed": 0,
"RPS Interrupts": 0,
"IPI Enqueued": 0,
"InputQ Dequeued": 0,
"Input Pkts": 0
},
{
"CPU": 32,
"Processed": 0,
"Dropped": 0,
"Squeezed": 0,
"RPS Interrupts": 0,
"IPI Enqueued": 0,
"InputQ Dequeued": 0,
"Input Pkts": 0
},
{
"CPU": 33,
"Processed": 0,
"Dropped": 0,
"Squeezed": 0,
"RPS Interrupts": 0,
"IPI Enqueued": 0,
"InputQ Dequeued": 0,
"Input Pkts": 0
},
{
"CPU": 34,
"Processed": 0,
"Dropped": 0,
"Squeezed": 0,
"RPS Interrupts": 0,
"IPI Enqueued": 0,
"InputQ Dequeued": 0,
"Input Pkts": 0
},
{
"CPU": 35,
"Processed": 0,
"Dropped": 0,
"Squeezed": 0,
"RPS Interrupts": 0,
"IPI Enqueued": 0,
"InputQ Dequeued": 0,
"Input Pkts": 0
}
]